lmstudio-1.4.0.dist-info/METADATA
lmstudio-1.4.0.dist-info/WHEEL
lmstudio-1.4.0.dist-info/entry_points.txt
lmstudio-1.4.0.dist-info/licenses/LICENSE
lmstudio/__init__.py
lmstudio/_kv_config.py
lmstudio/_logging.py
lmstudio/_sdk_models/README.md
lmstudio/_sdk_models/__init__.py
lmstudio/_ws_impl.py
lmstudio/async_api.py
lmstudio/history.py
lmstudio/json_api.py
lmstudio/py.typed
lmstudio/schemas.py
lmstudio/sdk_api.py
lmstudio/sync_api.py
lmstudio-1.4.0.dist-info/RECORD
