Metadata-Version: 2.4
Name: lmstudio
Version: 1.4.0
Summary: LM Studio Python SDK
Author-Email: LM Studio <team@lmstudio.ai>
Maintainer-Email: Alyssa Coghlan <ncoghlan@gmail.com>, Christian Zhou-Zheng <christianzhouzheng@gmail.com>
License-Expression: MIT
License-File: LICENSE
Classifier: Development Status :: 5 - Production/Stable
Classifier: Programming Language :: Python :: 3
Classifier: Programming Language :: Python :: 3.10
Classifier: Programming Language :: Python :: 3.11
Classifier: Programming Language :: Python :: 3.12
Classifier: Programming Language :: Python :: 3.13
Classifier: Topic :: Scientific/Engineering :: Artificial Intelligence
Classifier: Typing :: Typed
Project-URL: Homepage, https://github.com/lmstudio-ai/lmstudio-sdk-python
Project-URL: Documentation, https://lmstudio.ai/docs/sdk/
Project-URL: Issues, https://github.com/lmstudio-ai/lmstudio-sdk-python/issues
Requires-Python: >=3.10
Requires-Dist: httpx>=0.27.2
Requires-Dist: httpx-ws>=0.7.0
Requires-Dist: msgspec>=0.18.6
Requires-Dist: msgspec>=0.19.0; python_version >= "3.13"
Requires-Dist: typing-extensions>=4.12.2
Requires-Dist: anyio>=4.8.0
